<?xml version="1.0" encoding="UTF-8"?>
<Composants>
  <bread classe="Bread">
    <name>Italien</name>
    <photo />
    <allergens />
    <available>true</available>
    <new>false</new>
  </bread>
  <bread classe="Bread">
    <name>Wrap</name>
    <photo />
    <allergens />
    <available>false</available>
    <new>false</new>
  </bread>
  <bread classe="Bread">
    <name>Miel Avoine</name>
    <photo />
    <allergens />
    <available>true</available>
    <new>false</new>
  </bread>
  <bread classe="Bread">
    <name>Parmesan Origan</name>
    <photo />
    <allergens />
    <available>true</available>
    <new>false</new>
  </bread>
  <bread classe="Bread">
    <name>Blanc</name>
    <photo />
    <allergens />
    <available>true</available>
    <new>false</new>
  </bread>
  <garnish classe="Garnish">
    <name>Laitue</name>
    <photo />
    <allergens />
    <available>false</available>
    <new>false</new>
  </garnish>
  <garnish classe="Garnish">
    <name>Tomate</name>
    <photo />
    <allergens />
    <available>true</available>
    <new>false</new>
  </garnish>
  <garnish classe="Garnish">
    <name>Olive noire</name>
    <photo />
    <allergens />
    <available>true</available>
    <new>false</new>
  </garnish>
  <garnish classe="Garnish">
    <name>Concombre</name>
    <photo />
    <allergens />
    <available>true</available>
    <new>false</new>
  </garnish>
  <garnish classe="Garnish">
    <name>Mais</name>
    <photo />
    <allergens />
    <available>true</available>
    <new>true</new>
  </garnish>
  <garnish classe="Garnish">
    <name>Carottes rapée</name>
    <photo />
    <allergens />
    <available>false</available>
    <new>true</new>
  </garnish>
  <sauce classe="Sauce">
    <name>Barbecue</name>
    <photo />
    <allergens />
    <available>true</available>
    <new>false</new>
  </sauce>
  <sauce classe="Sauce">
    <name>Ketchup</name>
    <photo />
    <allergens />
    <available>false</available>
    <new>false</new>
  </sauce>
  <sauce classe="Sauce">
    <name>Ranch</name>
    <photo />
    <allergens />
    <available>false</available>
    <new>false</new>
  </sauce>
  <sauce classe="Sauce">
    <name>Miel Moutarde</name>
    <photo />
    <allergens />
    <available>false</available>
    <new>false</new>
  </sauce>
  <sauce classe="Sauce">
    <name>Mayonnaise</name>
    <photo />
    <allergens />
    <available>false</available>
    <new>false</new>
  </sauce>
  <recipe classe="Recipe">
    <name>Thon</name>
    <photo>..\images\thon.png</photo>
    <allergens />
    <price>7.0</price>
    <category>Mouais</category>
    <available>true</available>
    <new>false</new>
  </recipe>
  <recipe classe="Recipe">
    <name>Dinde</name>
    <photo />
    <allergens />
    <price>5.5</price>
    <category>Ca passe</category>
    <available>true</available>
    <new>false</new>
  </recipe>
  <recipe classe="Recipe">
    <name>Jambon</name>
    <photo />
    <allergens />
    <price>5.5</price>
    <category>Ca passe</category>
    <available>true</available>
    <new>false</new>
  </recipe>
  <recipe classe="Recipe">
    <name>Poulet</name>
    <photo />
    <allergens />
    <price>6.0</price>
    <category>Bof</category>
    <available>true</available>
    <new>false</new>
  </recipe>
  <recipe classe="Recipe">
    <name>MeetBall</name>
    <photo />
    <allergens />
    <price>7.0</price>
    <category>Mouais</category>
    <available>true</available>
    <new>false</new>
  </recipe>
  <drink classe="Drink">
    <name>Cola cola</name>
    <photo>toto</photo>
    <allergens />
    <available>true</available>
    <new>false</new>
  </drink>
  <drink classe="Drink">
    <name>Spiter</name>
    <photo />
    <allergens />
    <available>true</available>
    <new>false</new>
  </drink>
  <drink classe="Drink">
    <name>Iced Tea</name>
    <photo />
    <allergens />
    <available>true</available>
    <new>false</new>
  </drink>
  <drink classe="Drink">
    <name>Evina</name>
    <photo />
    <allergens />
    <available>true</available>
    <new>false</new>
  </drink>
  <dessert classe="Dessert">
    <name>brownie</name>
    <photo>truc marron</photo>
    <allergens />
    <available>true</available>
    <new>false</new>
  </dessert>
  <promo classe="Promotion">
    <name>Les pieds dans l'eau</name>
    <recipe>Thon</recipe>
    <category />
    <authCustomerOnly>true</authCustomerOnly>
    <percentage>20.0</percentage>
    <date>31082017</date>
  </promo>
  <promo classe="Promotion">
    <name>Ca passe à la trappe</name>
    <recipe />
    <category>Ca passe</category>
    <authCustomerOnly>false</authCustomerOnly>
    <percentage>10.0</percentage>
    <date>01012018</date>
  </promo>
</Composants>
